mercati_energetici/__init__.py
mercati_energetici/electricity_markets.py
mercati_energetici/energy_markets.py
mercati_energetici/environmental_markets.py
mercati_energetici/exceptions.py
mercati_energetici/gas_markets.py
mercati_energetici-0.1.0.dist-info/LICENSE.md
mercati_energetici-0.1.0.dist-info/METADATA
mercati_energetici-0.1.0.dist-info/WHEEL
mercati_energetici-0.1.0.dist-info/RECORD
