Metadata-Version: 2.1
Name: mercati-energetici
Version: 0.1.0
Summary: Unofficial python wrapper for the Italian energy markets API.
Author: Davide Marcato
Requires-Python: >=3.10,<4.0
Classifier: Programming Language :: Python :: 3
Classifier: Programming Language :: Python :: 3.10
Classifier: Programming Language :: Python :: 3.11
Requires-Dist: aiohttp (>=3.8.4,<4.0.0)
Requires-Dist: yarl (>=1.8.2,<2.0.0)
